nxneo4j/__init__.py
nxneo4j/base_graph.py
nxneo4j/centrality.py
nxneo4j/community.py
nxneo4j/di_graph.py
nxneo4j/graph.py
nxneo4j/path_finding.py
networkx_neo4j-0.0.2.dist-info/LICENSE
networkx_neo4j-0.0.2.dist-info/METADATA
networkx_neo4j-0.0.2.dist-info/WHEEL
networkx_neo4j-0.0.2.dist-info/top_level.txt
networkx_neo4j-0.0.2.dist-info/RECORD
