Metadata-Version: 2.1
Name: networkx-neo4j
Version: 0.0.2
Summary: NetworkX API for Neo4j Graph Algorithms
Home-page: http://markhneedham.com
Author: Mark Needham
Author-email: m.h.needham@gmal.com
Maintainer: Mark Needham
Maintainer-email: m.h.needham@gmal.com
License: Apache 2
Keywords: neo4j,networkx
Platform: All
Requires-Dist: neo4j-driver
